<?xml version="1.0"?>
<col:collection xmlns="http://cnx.rice.edu/collxml" xmlns:col="http://cnx.rice.edu/collxml" xml:lang="en" type="Course" authors="Mark Husband">\012  <metadata xmlns:md="http://cnx.rice.edu/mdml" mdml-version="0.5">\012  <md:content-id>col10257</md:content-id>\012  <md:title>Radar Jammer in Matlab</md:title>\012  \012  \012  <md:license url="http://creativecommons.org/licenses/by/2.0/">Creative Commons Attribution License 2.0</md:license>\012  <md:language>en</md:language>\012\012  \012\012  \012  \012  <md:uuid>1da7fc11-0def-4c16-85bc-9d8358dd9784</md:uuid>
<md:slug>radar-jammer-in-matlab</md:slug>
</metadata>\012\012  <col:content>\012    \012      <col:module document="m12575"/>\012        \012      \012    \012    \012      <col:module document="m12576"/>\012        \012      \012    \012    \012      <col:module document="m12577"/>\012        \012      \012    \012    \012      <col:module document="m12578"/>\012        \012      \012    \012    \012      <col:module document="m12579"/>\012        \012      \012    \012    \012      <col:module document="m12580"/>\012        \012      \012    \012    \012      <col:module document="m12581"/>\012        \012      \012    \012    \012      <col:module document="m12582"/>\012        \012      \012    \012  </col:content>\012</col:collection>
